icv/__init__.py
icv/__version__.py
icv/core/__init__.py
icv/core/errors.py
icv/data/__init__.py
icv/model/__init__.py
icv/model/build.py
icv/utils/__init__.py
icv/vis/__init__.py
icv/vis/show.py
icv-0.0.1.1.dist-info/DESCRIPTION.rst
icv-0.0.1.1.dist-info/METADATA
icv-0.0.1.1.dist-info/RECORD
icv-0.0.1.1.dist-info/WHEEL
icv-0.0.1.1.dist-info/metadata.json
icv-0.0.1.1.dist-info/top_level.txt
