Metadata-Version: 2.0
Name: icv
Version: 0.0.1.1
Summary: some common code and tools for computing version
Home-page: https://github.com/dmxj/icv
Author: rensike
Author-email: rensike@baidu.com
License: MIT
Platform: UNKNOWN
Classifier: License :: OSI Approved :: MIT License
Classifier: Programming Language :: Python
Classifier: Programming Language :: Python :: 3
Classifier: Programming Language :: Python :: 3.6
Classifier: Programming Language :: Python :: Implementation :: CPython
Classifier: Programming Language :: Python :: Implementation :: PyPy
Requires-Python: >=3.6.0
Requires-Dist: Pillow
Requires-Dist: numpy
